README.md
h5cat.py
setup.py
h5cat.egg-info/PKG-INFO
h5cat.egg-info/SOURCES.txt
h5cat.egg-info/dependency_links.txt
h5cat.egg-info/entry_points.txt
h5cat.egg-info/top_level.txt