Metadata-Version: 1.0
Name: h5cat
Version: 0.1
Summary: Quick preview of hdf5 files
Home-page: https://github.com/jni/h5cat
Author: Juan Nunez-Iglesias
Author-email: juan.nunez-iglesias@monash.edu
License: BSD 3-clause
Platform: UNKNOWN
